craft_grammar/__init__.py
craft_grammar/_base_processor.py
craft_grammar/_compound.py
craft_grammar/_for.py
craft_grammar/_on.py
craft_grammar/_processor.py
craft_grammar/_statement.py
craft_grammar/_to.py
craft_grammar/_try.py
craft_grammar/_types.py
craft_grammar/_version.py
craft_grammar/create.py
craft_grammar/errors.py
craft_grammar/models.py
craft_grammar/py.typed
craft_grammar-2.3.0.dist-info/licenses/LICENSE
craft_grammar-2.3.0.dist-info/METADATA
craft_grammar-2.3.0.dist-info/WHEEL
craft_grammar-2.3.0.dist-info/top_level.txt
craft_grammar-2.3.0.dist-info/RECORD
