Metadata-Version: 2.4
Name: craft-grammar
Version: 2.3.0
Summary: Provide python interfaces for using advanced grammar in craft-parts
License-Expression: GPL-3.0
Classifier: Development Status :: 5 - Production/Stable
Classifier: Programming Language :: Python :: 3
Classifier: Programming Language :: Python :: 3.10
Classifier: Programming Language :: Python :: 3.12
Requires-Python: >=3.10
License-File: LICENSE
Requires-Dist: overrides
Requires-Dist: pydantic~=2.0
Dynamic: license-file
